{
  "title": "Démarrer du bon pied avec Kaniko",
  "description": "Kaniko est un outil open source permettant de constuire des images de conteneurs depuis un conteneur, sans interagir avec le démon Docker.",
  "details": {
    "assets": {
        "host01": [
            {"file": "wait.sh", "chmod": "+x"},
            {"file": "registry.yaml"},
            {"file": "config.json"}
        ]
    },
    "steps": [
      {
        "title": "Constuire une image Docker localement",
        "text": "step1.md"
      },
      {
        "title": "Construire une image Docker sur K8S",
        "text": "step2.md",
        "code": "waitForKub.sh"
      },
      {
        "title": "Constuire une image Docker sur K8S en utilisant le démon",
        "text": "step3.md",
        "courseData": "friends.sh"
      },
      {
        "title": "Constuire une image Docker localement en utilisant Kaniko",
        "text": "step4.md"
      },
      {
        "title": "Constuire une image Docker sur K8S en utilisant Kaniko",
        "text": "step5.md"
      }
    ],
    "intro": {
      "text": "intro.md",
      "courseData": "background.sh"
    },
    "finish": {
      "text": "finish.md"
    }
  },
  "environment": {
    "uilayout": "terminal-terminal",
    "uimessage1": "\u001b[32mTerminal interactif - K8S.\u001b[m\r\n"
  },
  "backend": {
    "imageid": "kubernetes-cluster-running:1.18"
  }
}
